tkShadow/__init__.py
tkShadow-1.0.3.1.dist-info/LICENSE
tkShadow-1.0.3.1.dist-info/METADATA
tkShadow-1.0.3.1.dist-info/WHEEL
tkShadow-1.0.3.1.dist-info/top_level.txt
tkShadow-1.0.3.1.dist-info/RECORD
