Metadata-Version: 2.1
Name: tkShadow
Version: 1.0.3.1
Summary: 在您的 tkinter 项目上为控件或 Canvas 元素添加阴影
Home-page: https://github.com/codecrafter-tl/tkshadow
Author: CodeCrafter-TL
Author-email: CodeCrafter-TL <1825456084@qq.com>
Project-URL: GitHub, https://github.com/codecrafter-tl/tkshadow
Project-URL: PyPI, https://pypi.org/project/tkshadow
Classifier: Programming Language :: Python :: 3
Classifier: License :: OSI Approved :: MIT License
Classifier: Operating System :: OS Independent
Requires-Python: >=3.10
License-File: LICENSE
